wppkg/__init__.py
wppkg/dl.py
wppkg/logging.py
wppkg/sc.py
wppkg/utils.py
wppkg/debugpy_config/launch.json
wppkg/deepspeed_config/zero1.json
wppkg/deepspeed_config/zero2.json
wppkg/deepspeed_config/zero2_offload.json
wppkg/deepspeed_config/zero3.json
wppkg/deepspeed_config/zero3_offload.json
wppkg-0.1.2.dist-info/METADATA
wppkg-0.1.2.dist-info/WHEEL
wppkg-0.1.2.dist-info/licenses/LICENSE
wppkg-0.1.2.dist-info/RECORD
