Metadata-Version: 2.4
Name: wppkg
Version: 0.1.2
Summary: A package I developed for my daily work.
Project-URL: Homepage, https://github.com/Peg-Wu/wppkg
Project-URL: Issues, https://github.com/Peg-Wu/wppkg/issues
Author-email: Pengpeng Wu <peg2_wu@163.com>
License-Expression: MIT
License-File: LICENSE
Keywords: wppkg
Classifier: Operating System :: OS Independent
Classifier: Programming Language :: Python :: 3
Requires-Python: >=3.10
Requires-Dist: accelerate
Requires-Dist: bitsandbytes
Requires-Dist: datasets
Requires-Dist: debugpy
Requires-Dist: easydict
Requires-Dist: evaluate
Requires-Dist: joblib
Requires-Dist: matplotlib
Requires-Dist: peft
Requires-Dist: scanpy
Requires-Dist: tensorboard
Requires-Dist: torch
Requires-Dist: transformers
Requires-Dist: trl
